ctdproc/__init__.py
ctdproc/calcs.py
ctdproc/helpers.py
ctdproc/io.py
ctdproc/proc.py
ctdproc-0.2.0.dist-info/licenses/LICENSE
ctdproc-0.2.0.dist-info/WHEEL
ctdproc-0.2.0.dist-info/METADATA
ctdproc-0.2.0.dist-info/RECORD
