Metadata-Version: 2.4
Name: ctdproc
Version: 0.2.0
Summary: CTD data processing
Author: Gunnar Voet
Author-email: Gunnar Voet <gvoet@ucsd.edu>
License-Expression: MIT
License-File: LICENSE
Classifier: Development Status :: 4 - Beta
Classifier: Intended Audience :: Science/Research
Classifier: Topic :: Scientific/Engineering :: Physics
Classifier: License :: OSI Approved :: MIT License
Classifier: Natural Language :: English
Classifier: Programming Language :: Python :: 3
Requires-Dist: gsw>=3.6.20
Requires-Dist: matplotlib>=3.9.4
Requires-Dist: munch>=4.0.0
Requires-Dist: netcdf4>=1.7.2
Requires-Dist: numpy>=2.0.2
Requires-Dist: pandas>=2.3.3
Requires-Dist: scipy>=1.13.1
Requires-Dist: xarray>=2024.7.0
Requires-Dist: xmltodict>=1.0.2
Requires-Python: >=3.9
Project-URL: Bug Tracker, https://github.com/gunnarvoet/ctdproc/issues
Project-URL: Changelog, https://github.com/gunnarvoet/ctdproc/blob/main/HISTORY.rst
Project-URL: Documentation, https://ctdproc.readthedocs.io
Project-URL: Homepage, https://github.com/gunnarvoet/ctdproc
